{
  "generatedAt": "2026-04-15T11:19:47.402Z",
  "boardSize": "150",
  "pieceSize": "150",
  "defaultBoardTheme": "burled_wood",
  "defaultPieceTheme": "glass",
  "boardAssets": {
    "8_bit": "/boards/8_bit.png",
    "bases": "/boards/bases.jpg",
    "translucent": "/boards/translucent.png",
    "blue": "/boards/blue.png",
    "brown": "/boards/brown.png",
    "bubblegum": "/boards/bubblegum.png",
    "burled_wood": "/boards/burled_wood.jpg",
    "checkers": "/boards/checkers.png",
    "dark_wood": "/boards/dark_wood.jpg",
    "dash": "/boards/dash.jpg",
    "green": "/boards/green.png",
    "glass": "/boards/glass.png",
    "graffiti": "/boards/graffiti.jpg",
    "light": "/boards/light.png",
    "icy_sea": "/boards/icy_sea.jpg",
    "lolz": "/boards/lolz.jpg",
    "marble": "/boards/marble.jpg",
    "metal": "/boards/metal.jpg",
    "tan": "/boards/tan.png",
    "neon": "/boards/neon.png",
    "newspaper": "/boards/newspaper.jpg",
    "orange": "/boards/orange.png",
    "overlay": "/boards/overlay.png",
    "parchment": "/boards/parchment.jpg",
    "purple": "/boards/purple.png",
    "red": "/boards/red.png",
    "sand": "/boards/sand.jpg",
    "sky": "/boards/sky.png",
    "stone": "/boards/stone.jpg",
    "tournament": "/boards/tournament.jpg",
    "walnut": "/boards/walnut.jpg",
    "blackwhite": "/boards/translucent.png",
    "default": "/boards/green.png",
    "grey": "/boards/light.png",
    "marblebrown": "/boards/graffiti.jpg",
    "natural": "/boards/tan.png",
    "pink": "/boards/bubblegum.png",
    "winboard": "/boards/tournament.jpg",
    "wood": "/boards/dark_wood.jpg",
    "wooddark": "/boards/burled_wood.jpg",
    "woodlight": "/boards/parchment.jpg",
    "woodmid": "/boards/dark_wood.jpg"
  },
  "pieceAssets": {
    "3d_staunton": "/pieces/3d_staunton/150",
    "3d_chesskid": "/pieces/3d_chesskid/150",
    "3d_plastic": "/pieces/3d_plastic/150",
    "3d_wood": "/pieces/3d_wood/150",
    "8_bit": "/pieces/8_bit/150",
    "alpha": "/pieces/alpha/150",
    "bases": "/pieces/bases/150",
    "blindfold": "/pieces/blindfold/150",
    "book": "/pieces/book/150",
    "bubblegum": "/pieces/bubblegum/150",
    "cases": "/pieces/cases/150",
    "classic": "/pieces/classic/150",
    "club": "/pieces/club/150",
    "condal": "/pieces/condal/150",
    "dash": "/pieces/dash/150",
    "game_room": "/pieces/game_room/150",
    "glass": "/pieces/glass/150",
    "gothic": "/pieces/gothic/150",
    "graffiti": "/pieces/graffiti/150",
    "icy_sea": "/pieces/icy_sea/150",
    "light": "/pieces/light/150",
    "lolz": "/pieces/lolz/150",
    "luca": "/pieces/luca/150",
    "marble": "/pieces/marble/150",
    "maya": "/pieces/maya/150",
    "metal": "/pieces/metal/150",
    "modern": "/pieces/modern/150",
    "nature": "/pieces/nature/150",
    "neo": "/pieces/neo/150",
    "neo_wood": "/pieces/neo_wood/150",
    "neon": "/pieces/neon/150",
    "newspaper": "/pieces/newspaper/150",
    "ocean": "/pieces/ocean/150",
    "sky": "/pieces/sky/150",
    "space": "/pieces/space/150",
    "tigers": "/pieces/tigers/150",
    "tournament": "/pieces/tournament/150",
    "vintage": "/pieces/vintage/150",
    "wood": "/pieces/wood/150",
    "3dplastic": "/pieces/3d_plastic/150",
    "3dwood": "/pieces/3d_wood/150",
    "3dchesskid": "/pieces/3d_chesskid/150",
    "modern2": "/pieces/modern/150",
    "real3d": "/pieces/neo/150"
  },
  "boardThemes": [
    "8_bit",
    "bases",
    "blackwhite",
    "blue",
    "brown",
    "bubblegum",
    "burled_wood",
    "checkers",
    "dark_wood",
    "dash",
    "default",
    "glass",
    "graffiti",
    "green",
    "grey",
    "icy_sea",
    "light",
    "lolz",
    "marble",
    "marblebrown",
    "metal",
    "natural",
    "neon",
    "newspaper",
    "orange",
    "overlay",
    "parchment",
    "pink",
    "purple",
    "red",
    "sand",
    "sky",
    "stone",
    "tan",
    "tournament",
    "translucent",
    "walnut",
    "winboard",
    "wood",
    "wooddark",
    "woodlight",
    "woodmid"
  ],
  "pieceThemes": [
    "3d_chesskid",
    "3d_plastic",
    "3d_staunton",
    "3d_wood",
    "3dchesskid",
    "3dplastic",
    "3dwood",
    "8_bit",
    "alpha",
    "bases",
    "blindfold",
    "book",
    "bubblegum",
    "cases",
    "classic",
    "club",
    "condal",
    "dash",
    "game_room",
    "glass",
    "gothic",
    "graffiti",
    "icy_sea",
    "light",
    "lolz",
    "luca",
    "marble",
    "maya",
    "metal",
    "modern",
    "modern2",
    "nature",
    "neo",
    "neo_wood",
    "neon",
    "newspaper",
    "ocean",
    "real3d",
    "sky",
    "space",
    "tigers",
    "tournament",
    "vintage",
    "wood"
  ]
}
